odoo/addons/ssi_py3o_print_mixin/README.rst
odoo/addons/ssi_py3o_print_mixin/__init__.py
odoo/addons/ssi_py3o_print_mixin/__manifest__.py
odoo/addons/ssi_py3o_print_mixin/models/__init__.py
odoo/addons/ssi_py3o_print_mixin/models/ir_actions_report.py
odoo/addons/ssi_py3o_print_mixin/static/description/icon.png
odoo14_addon_ssi_py3o_print_mixin-14.0.1.0.0.dist-info/METADATA
odoo14_addon_ssi_py3o_print_mixin-14.0.1.0.0.dist-info/WHEEL
odoo14_addon_ssi_py3o_print_mixin-14.0.1.0.0.dist-info/top_level.txt
odoo14_addon_ssi_py3o_print_mixin-14.0.1.0.0.dist-info/RECORD
